tab2latex/__init__.py
tab2latex/textable.py
tab2latex/test/__init__.py
tab2latex/test/test_tab2latex.py
tab2latex-0.1.7.dist-info/LICENSE
tab2latex-0.1.7.dist-info/METADATA
tab2latex-0.1.7.dist-info/WHEEL
tab2latex-0.1.7.dist-info/top_level.txt
tab2latex-0.1.7.dist-info/RECORD
