Metadata-Version: 2.1
Name: tab2latex
Version: 0.1.7
Summary: A small Python package that puts your numpy arrays into latex files using the table/longtable environment
Home-page: https://github.com/Julian-Hochhaus/py_modules/tree/master/modules/tab2latex
Author: Julian Hochhaus
Author-email: julian.hochhaus@tu-dortmund.de
License: MIT
Platform: UNKNOWN
Classifier: Programming Language :: Python :: 3
Classifier: License :: OSI Approved :: MIT License
Classifier: Operating System :: OS Independent
